{"cameraMode":{"drawMode":0,"name":"Shaded","section":"Shading Mode"},"sceneLighting":true,"audioPlay":false,"sceneViewState":{"showFog":true,"showMaterialUpdate":false,"showSkybox":true,"showFlares":true,"showImageEffects":true,"showParticleSystems":true},"in2DMode":false,"pivot":{"x":0.07363171875476837,"y":-0.2974469065666199,"z":1.209092378616333},"rotation":{"x":-0.1080721840262413,"y":-0.021772610023617746,"z":0.002367418259382248,"w":-0.993901789188385},"size":1.6007227897644044,"orthographic":false}